mlflow_aws_rds_iam/__init__.py
mlflow_aws_rds_iam/certs/global-bundle.pem
mlflow_aws_rds_iam/listeners.py
mlflow_aws_rds_iam/model_registry.py
mlflow_aws_rds_iam/ssl.py
mlflow_aws_rds_iam/tracking.py
mlflow_aws_rds_iam/utils.py
mlflow_aws_rds_iam-0.3.0.dist-info/LICENSE.md
mlflow_aws_rds_iam-0.3.0.dist-info/METADATA
mlflow_aws_rds_iam-0.3.0.dist-info/WHEEL
mlflow_aws_rds_iam-0.3.0.dist-info/entry_points.txt
mlflow_aws_rds_iam-0.3.0.dist-info/RECORD
