Metadata-Version: 2.1
Name: mlflow-aws-rds-iam
Version: 0.3.0
Summary: MLflow plugins adding AWS RDS IAM auth for tracking and model registry stores
Home-page: https://gitlab.com/lzinsou/mlflow-aws-rds-iam
Keywords: mlflow,plugin,mlops,aws,rds,iam,postgresql,mysql
Author: Loris Zinsou
Author-email: lzinsou@protonmail.com
Requires-Python: >=3.10,<4.0
Classifier: Development Status :: 3 - Alpha
Classifier: Environment :: Plugins
Classifier: Programming Language :: Python :: 3
Classifier: Programming Language :: Python :: 3.10
Classifier: Programming Language :: Python :: 3.11
Classifier: Programming Language :: Python :: 3.12
Classifier: Programming Language :: Python :: 3.13
Requires-Dist: StrEnum (>=0.4) ; python_version < "3.11"
Requires-Dist: boto3 (>=1.26,<2)
Requires-Dist: boto3-stubs[rds] (>=1.26,<2)
Requires-Dist: mlflow (>=2,<3)
Requires-Dist: sqlalchemy (>=2.0.24)
Project-URL: Repository, https://gitlab.com/lzinsou/mlflow-aws-rds-iam
